sopy_fem/__init__.py
sopy_fem/assembly.py
sopy_fem/bars_utils.py
sopy_fem/dmat.py
sopy_fem/gauss_quadrature.py
sopy_fem/globalvars.py
sopy_fem/initialization.py
sopy_fem/plot_solids.py
sopy_fem/plot_trusses.py
sopy_fem/postprocess.py
sopy_fem/read_data.py
sopy_fem/solids_utils.py
sopy_fem/solver.py
sopy_fem/sopy_fem_help.py
sopy_fem/sopy_fem_run.py
sopy_fem/Examples/dynamics_FRAME02/data.json
sopy_fem/Examples/dynamics_TRUSS02/data.json
sopy_fem/Examples/electrical_BR02/data.json
sopy_fem/Examples/mechanics_BR02/data.json
sopy_fem/Examples/mechanics_QU04/data.json
sopy_fem/Examples/mechanics_TR03/data.json
sopy_fem/Examples/structural_FRAME02/data.json
sopy_fem/Examples/structural_TRUSS02/data.json
sopy_fem/Examples/thermal_BR02/data.json
sopy_fem-1.1.0.dist-info/licenses/LICENSE
sopy_fem-1.1.0.dist-info/METADATA
sopy_fem-1.1.0.dist-info/WHEEL
sopy_fem-1.1.0.dist-info/top_level.txt
sopy_fem-1.1.0.dist-info/RECORD
