Metadata-Version: 2.4
Name: sopy_fem
Version: 1.1.0
Summary: An academic program for finite elments analysis of 2D solids and structures
Home-page: https://github.com/DanielDiCapua/sopy_fem.git
Download-URL: https://github.com/DanielDiCapua/sopy_fem.git/tarball/1.1.0
Author: Daniel Di Capua
Author-email: dicapua67@gmail.com
Keywords: developing,example
License-File: LICENSE
Dynamic: author
Dynamic: author-email
Dynamic: download-url
Dynamic: home-page
Dynamic: keywords
Dynamic: license-file
Dynamic: summary
